<?xml version="1.0" encoding="UTF-8"?>
<battle_maps>
  <entry>
    <key>BATTLEMAP_01senate</key>
    <xi:include xmlns:xi="http://www.w3.org/2001/XInclude" href="BATTLEMAP_01senate.xml" />
  </entry>
  <entry>
    <key>BATTLEMAP_02police</key>
    <xi:include xmlns:xi="http://www.w3.org/2001/XInclude" href="BATTLEMAP_02police.xml" />
  </entry>
  <entry>
    <key>BATTLEMAP_03hospit</key>
    <xi:include xmlns:xi="http://www.w3.org/2001/XInclude" href="BATTLEMAP_03hospit.xml" />
  </entry>
  <entry>
    <key>BATTLEMAP_04school</key>
    <xi:include xmlns:xi="http://www.w3.org/2001/XInclude" href="BATTLEMAP_04school.xml" />
  </entry>
  <entry>
    <key>BATTLEMAP_05rescue</key>
    <xi:include xmlns:xi="http://www.w3.org/2001/XInclude" href="BATTLEMAP_05rescue.xml" />
  </entry>
  <entry>
    <key>BATTLEMAP_06office</key>
    <xi:include xmlns:xi="http://www.w3.org/2001/XInclude" href="BATTLEMAP_06office.xml" />
  </entry>
  <entry>
    <key>BATTLEMAP_07corphq</key>
    <xi:include xmlns:xi="http://www.w3.org/2001/XInclude" href="BATTLEMAP_07corphq.xml" />
  </entry>
  <entry>
    <key>BATTLEMAP_08port</key>
    <xi:include xmlns:xi="http://www.w3.org/2001/XInclude" href="BATTLEMAP_08port.xml" />
  </entry>
  <entry>
    <key>BATTLEMAP_10astro</key>
    <xi:include xmlns:xi="http://www.w3.org/2001/XInclude" href="BATTLEMAP_10astro.xml" />
  </entry>
  <entry>
    <key>BATTLEMAP_11park</key>
    <xi:include xmlns:xi="http://www.w3.org/2001/XInclude" href="BATTLEMAP_11park.xml" />
  </entry>
  <entry>
    <key>BATTLEMAP_12shops</key>
    <xi:include xmlns:xi="http://www.w3.org/2001/XInclude" href="BATTLEMAP_12shops.xml" />
  </entry>
  <entry>
    <key>BATTLEMAP_14acnorm</key>
    <xi:include xmlns:xi="http://www.w3.org/2001/XInclude" href="BATTLEMAP_14acnorm.xml" />
  </entry>
  <entry>
    <key>BATTLEMAP_15acposh</key>
    <xi:include xmlns:xi="http://www.w3.org/2001/XInclude" href="BATTLEMAP_15acposh.xml" />
  </entry>
  <entry>
    <key>BATTLEMAP_18hydro</key>
    <xi:include xmlns:xi="http://www.w3.org/2001/XInclude" href="BATTLEMAP_18hydro.xml" />
  </entry>
  <entry>
    <key>BATTLEMAP_19sewage</key>
    <xi:include xmlns:xi="http://www.w3.org/2001/XInclude" href="BATTLEMAP_19sewage.xml" />
  </entry>
  <entry>
    <key>BATTLEMAP_20water</key>
    <xi:include xmlns:xi="http://www.w3.org/2001/XInclude" href="BATTLEMAP_20water.xml" />
  </entry>
  <entry>
    <key>BATTLEMAP_21appl</key>
    <xi:include xmlns:xi="http://www.w3.org/2001/XInclude" href="BATTLEMAP_21appl.xml" />
  </entry>
  <entry>
    <key>BATTLEMAP_22arms</key>
    <xi:include xmlns:xi="http://www.w3.org/2001/XInclude" href="BATTLEMAP_22arms.xml" />
  </entry>
  <entry>
    <key>BATTLEMAP_23robots</key>
    <xi:include xmlns:xi="http://www.w3.org/2001/XInclude" href="BATTLEMAP_23robots.xml" />
  </entry>
  <entry>
    <key>BATTLEMAP_25flyer</key>
    <xi:include xmlns:xi="http://www.w3.org/2001/XInclude" href="BATTLEMAP_25flyer.xml" />
  </entry>
  <entry>
    <key>BATTLEMAP_26lflyer</key>
    <xi:include xmlns:xi="http://www.w3.org/2001/XInclude" href="BATTLEMAP_26lflyer.xml" />
  </entry>
  <entry>
    <key>BATTLEMAP_27constr</key>
    <xi:include xmlns:xi="http://www.w3.org/2001/XInclude" href="BATTLEMAP_27constr.xml" />
  </entry>
  <entry>
    <key>BATTLEMAP_28slums</key>
    <xi:include xmlns:xi="http://www.w3.org/2001/XInclude" href="BATTLEMAP_28slums.xml" />
  </entry>
  <entry>
    <key>BATTLEMAP_30ware</key>
    <xi:include xmlns:xi="http://www.w3.org/2001/XInclude" href="BATTLEMAP_30ware.xml" />
  </entry>
  <entry>
    <key>BATTLEMAP_32power</key>
    <xi:include xmlns:xi="http://www.w3.org/2001/XInclude" href="BATTLEMAP_32power.xml" />
  </entry>
  <entry>
    <key>BATTLEMAP_33recycl</key>
    <xi:include xmlns:xi="http://www.w3.org/2001/XInclude" href="BATTLEMAP_33recycl.xml" />
  </entry>
  <entry>
    <key>BATTLEMAP_35tubes</key>
    <xi:include xmlns:xi="http://www.w3.org/2001/XInclude" href="BATTLEMAP_35tubes.xml" />
  </entry>
  <entry>
    <key>BATTLEMAP_36church</key>
    <xi:include xmlns:xi="http://www.w3.org/2001/XInclude" href="BATTLEMAP_36church.xml" />
  </entry>
  <entry>
    <key>BATTLEMAP_37base</key>
    <xi:include xmlns:xi="http://www.w3.org/2001/XInclude" href="BATTLEMAP_37base.xml" />
  </entry>
  <entry>
    <key>BATTLEMAP_39incub</key>
    <xi:include xmlns:xi="http://www.w3.org/2001/XInclude" href="BATTLEMAP_39incub.xml" />
  </entry>
  <entry>
    <key>BATTLEMAP_40spawn</key>
    <xi:include xmlns:xi="http://www.w3.org/2001/XInclude" href="BATTLEMAP_40spawn.xml" />
  </entry>
  <entry>
    <key>BATTLEMAP_41food</key>
    <xi:include xmlns:xi="http://www.w3.org/2001/XInclude" href="BATTLEMAP_41food.xml" />
  </entry>
  <entry>
    <key>BATTLEMAP_42megapd</key>
    <xi:include xmlns:xi="http://www.w3.org/2001/XInclude" href="BATTLEMAP_42megapd.xml" />
  </entry>
  <entry>
    <key>BATTLEMAP_43sleep</key>
    <xi:include xmlns:xi="http://www.w3.org/2001/XInclude" href="BATTLEMAP_43sleep.xml" />
  </entry>
  <entry>
    <key>BATTLEMAP_44organ</key>
    <xi:include xmlns:xi="http://www.w3.org/2001/XInclude" href="BATTLEMAP_44organ.xml" />
  </entry>
  <entry>
    <key>BATTLEMAP_45farm</key>
    <xi:include xmlns:xi="http://www.w3.org/2001/XInclude" href="BATTLEMAP_45farm.xml" />
  </entry>
  <entry>
    <key>BATTLEMAP_46contrl</key>
    <xi:include xmlns:xi="http://www.w3.org/2001/XInclude" href="BATTLEMAP_46contrl.xml" />
  </entry>
  <entry>
    <key>BATTLEMAP_47maint</key>
    <xi:include xmlns:xi="http://www.w3.org/2001/XInclude" href="BATTLEMAP_47maint.xml" />
  </entry>
  <entry>
    <key>BATTLEMAP_48gate</key>
    <xi:include xmlns:xi="http://www.w3.org/2001/XInclude" href="BATTLEMAP_48gate.xml" />
  </entry>
  <entry>
    <key>BATTLEMAP_50senso</key>
    <xi:include xmlns:xi="http://www.w3.org/2001/XInclude" href="BATTLEMAP_50senso.xml" />
  </entry>
  <entry>
    <key>BATTLEMAP_51ufo1</key>
    <xi:include xmlns:xi="http://www.w3.org/2001/XInclude" href="BATTLEMAP_51ufo1.xml" />
  </entry>
  <entry>
    <key>BATTLEMAP_52ufo2</key>
    <xi:include xmlns:xi="http://www.w3.org/2001/XInclude" href="BATTLEMAP_52ufo2.xml" />
  </entry>
  <entry>
    <key>BATTLEMAP_53ufo3</key>
    <xi:include xmlns:xi="http://www.w3.org/2001/XInclude" href="BATTLEMAP_53ufo3.xml" />
  </entry>
  <entry>
    <key>BATTLEMAP_54ufo4</key>
    <xi:include xmlns:xi="http://www.w3.org/2001/XInclude" href="BATTLEMAP_54ufo4.xml" />
  </entry>
  <entry>
    <key>BATTLEMAP_55ufo5</key>
    <xi:include xmlns:xi="http://www.w3.org/2001/XInclude" href="BATTLEMAP_55ufo5.xml" />
  </entry>
  <entry>
    <key>BATTLEMAP_56ufo6</key>
    <xi:include xmlns:xi="http://www.w3.org/2001/XInclude" href="BATTLEMAP_56ufo6.xml" />
  </entry>
  <entry>
    <key>BATTLEMAP_57ufo7</key>
    <xi:include xmlns:xi="http://www.w3.org/2001/XInclude" href="BATTLEMAP_57ufo7.xml" />
  </entry>
  <entry>
    <key>BATTLEMAP_58ufo8</key>
    <xi:include xmlns:xi="http://www.w3.org/2001/XInclude" href="BATTLEMAP_58ufo8.xml" />
  </entry>
</battle_maps>
