<?xml version="1.0" encoding="UTF-8"?>
<openapoc_rules>
  <vehicledef id="VEHICLE_AIRTRANS" name="STR_AIRTRANS_NAME" manufacturer="ORG_TRANSTELLAR" sizeX="1" sizeY="1" sizeZ="1" imageOffsetX="32" imageOffsetY="32" type="flying">
    <stratmap>
      <N>PCKSTRAT:xcom3/UFODATA/STRATMAP.PCK:xcom3/UFODATA/STRATMAP.TAB:577</N>
      <NE>PCKSTRAT:xcom3/UFODATA/STRATMAP.PCK:xcom3/UFODATA/STRATMAP.TAB:578</NE>
      <E>PCKSTRAT:xcom3/UFODATA/STRATMAP.PCK:xcom3/UFODATA/STRATMAP.TAB:579</E>
      <SE>PCKSTRAT:xcom3/UFODATA/STRATMAP.PCK:xcom3/UFODATA/STRATMAP.TAB:580</SE>
      <S>PCKSTRAT:xcom3/UFODATA/STRATMAP.PCK:xcom3/UFODATA/STRATMAP.TAB:581</S>
      <SW>PCKSTRAT:xcom3/UFODATA/STRATMAP.PCK:xcom3/UFODATA/STRATMAP.TAB:582</SW>
      <W>PCKSTRAT:xcom3/UFODATA/STRATMAP.PCK:xcom3/UFODATA/STRATMAP.TAB:583</W>
      <NW>PCKSTRAT:xcom3/UFODATA/STRATMAP.PCK:xcom3/UFODATA/STRATMAP.TAB:584</NW>
    </stratmap>
    <flat>
      <N>PCK:xcom3/UFODATA/SAUCER.PCK:xcom3/UFODATA/SAUCER.TAB:327</N>
      <NE>PCK:xcom3/UFODATA/SAUCER.PCK:xcom3/UFODATA/SAUCER.TAB:328</NE>
      <E>PCK:xcom3/UFODATA/SAUCER.PCK:xcom3/UFODATA/SAUCER.TAB:329</E>
      <SE>PCK:xcom3/UFODATA/SAUCER.PCK:xcom3/UFODATA/SAUCER.TAB:330</SE>
      <S>PCK:xcom3/UFODATA/SAUCER.PCK:xcom3/UFODATA/SAUCER.TAB:331</S>
      <SW>PCK:xcom3/UFODATA/SAUCER.PCK:xcom3/UFODATA/SAUCER.TAB:332</SW>
      <W>PCK:xcom3/UFODATA/SAUCER.PCK:xcom3/UFODATA/SAUCER.TAB:333</W>
      <NW>PCK:xcom3/UFODATA/SAUCER.PCK:xcom3/UFODATA/SAUCER.TAB:334</NW>
    </flat>
    <decending>
      <N>PCK:xcom3/UFODATA/SAUCER.PCK:xcom3/UFODATA/SAUCER.TAB:335</N>
      <NE>PCK:xcom3/UFODATA/SAUCER.PCK:xcom3/UFODATA/SAUCER.TAB:336</NE>
      <E>PCK:xcom3/UFODATA/SAUCER.PCK:xcom3/UFODATA/SAUCER.TAB:337</E>
      <SE>PCK:xcom3/UFODATA/SAUCER.PCK:xcom3/UFODATA/SAUCER.TAB:338</SE>
      <S>PCK:xcom3/UFODATA/SAUCER.PCK:xcom3/UFODATA/SAUCER.TAB:339</S>
      <SW>PCK:xcom3/UFODATA/SAUCER.PCK:xcom3/UFODATA/SAUCER.TAB:340</SW>
      <W>PCK:xcom3/UFODATA/SAUCER.PCK:xcom3/UFODATA/SAUCER.TAB:341</W>
      <NW>PCK:xcom3/UFODATA/SAUCER.PCK:xcom3/UFODATA/SAUCER.TAB:342</NW>
    </decending>
    <ascending>
      <N>PCK:xcom3/UFODATA/SAUCER.PCK:xcom3/UFODATA/SAUCER.TAB:343</N>
      <NE>PCK:xcom3/UFODATA/SAUCER.PCK:xcom3/UFODATA/SAUCER.TAB:344</NE>
      <E>PCK:xcom3/UFODATA/SAUCER.PCK:xcom3/UFODATA/SAUCER.TAB:345</E>
      <SE>PCK:xcom3/UFODATA/SAUCER.PCK:xcom3/UFODATA/SAUCER.TAB:346</SE>
      <S>PCK:xcom3/UFODATA/SAUCER.PCK:xcom3/UFODATA/SAUCER.TAB:347</S>
      <SW>PCK:xcom3/UFODATA/SAUCER.PCK:xcom3/UFODATA/SAUCER.TAB:348</SW>
      <W>PCK:xcom3/UFODATA/SAUCER.PCK:xcom3/UFODATA/SAUCER.TAB:349</W>
      <NW>PCK:xcom3/UFODATA/SAUCER.PCK:xcom3/UFODATA/SAUCER.TAB:350</NW>
    </ascending>
    <banking_right>
      <N>PCK:xcom3/UFODATA/SAUCER.PCK:xcom3/UFODATA/SAUCER.TAB:351</N>
      <NE>PCK:xcom3/UFODATA/SAUCER.PCK:xcom3/UFODATA/SAUCER.TAB:352</NE>
      <E>PCK:xcom3/UFODATA/SAUCER.PCK:xcom3/UFODATA/SAUCER.TAB:353</E>
      <SE>PCK:xcom3/UFODATA/SAUCER.PCK:xcom3/UFODATA/SAUCER.TAB:354</SE>
      <S>PCK:xcom3/UFODATA/SAUCER.PCK:xcom3/UFODATA/SAUCER.TAB:355</S>
      <SW>PCK:xcom3/UFODATA/SAUCER.PCK:xcom3/UFODATA/SAUCER.TAB:356</SW>
      <W>PCK:xcom3/UFODATA/SAUCER.PCK:xcom3/UFODATA/SAUCER.TAB:357</W>
      <NW>PCK:xcom3/UFODATA/SAUCER.PCK:xcom3/UFODATA/SAUCER.TAB:358</NW>
    </banking_right>
    <banking_left>
      <N>PCK:xcom3/UFODATA/SAUCER.PCK:xcom3/UFODATA/SAUCER.TAB:359</N>
      <NE>PCK:xcom3/UFODATA/SAUCER.PCK:xcom3/UFODATA/SAUCER.TAB:360</NE>
      <E>PCK:xcom3/UFODATA/SAUCER.PCK:xcom3/UFODATA/SAUCER.TAB:361</E>
      <SE>PCK:xcom3/UFODATA/SAUCER.PCK:xcom3/UFODATA/SAUCER.TAB:362</SE>
      <S>PCK:xcom3/UFODATA/SAUCER.PCK:xcom3/UFODATA/SAUCER.TAB:363</S>
      <SW>PCK:xcom3/UFODATA/SAUCER.PCK:xcom3/UFODATA/SAUCER.TAB:364</SW>
      <W>PCK:xcom3/UFODATA/SAUCER.PCK:xcom3/UFODATA/SAUCER.TAB:365</W>
      <NW>PCK:xcom3/UFODATA/SAUCER.PCK:xcom3/UFODATA/SAUCER.TAB:366</NW>
    </banking_left>
    <shadow>
      <N>PCKSHADOW:xcom3/UFODATA/SHADOW.PCK:xcom3/UFODATA/SHADOW.TAB:48</N>
      <NE>PCKSHADOW:xcom3/UFODATA/SHADOW.PCK:xcom3/UFODATA/SHADOW.TAB:49</NE>
      <E>PCKSHADOW:xcom3/UFODATA/SHADOW.PCK:xcom3/UFODATA/SHADOW.TAB:50</E>
      <SE>PCKSHADOW:xcom3/UFODATA/SHADOW.PCK:xcom3/UFODATA/SHADOW.TAB:51</SE>
      <S>PCKSHADOW:xcom3/UFODATA/SHADOW.PCK:xcom3/UFODATA/SHADOW.TAB:52</S>
      <SW>PCKSHADOW:xcom3/UFODATA/SHADOW.PCK:xcom3/UFODATA/SHADOW.TAB:53</SW>
      <W>PCKSHADOW:xcom3/UFODATA/SHADOW.PCK:xcom3/UFODATA/SHADOW.TAB:54</W>
      <NW>PCKSHADOW:xcom3/UFODATA/SHADOW.PCK:xcom3/UFODATA/SHADOW.TAB:55</NW>
    </shadow>
  </vehicledef>
</openapoc_rules>
