<?xml version="1.0" encoding="UTF-8"?>
<openapoc_rules>
  <vehicle id="VEHICLE_ALIEN_TRANSPORTER" type="ufo">
    <name>STR_ALIEN_TRANSPORTER</name>
    <manufacturer>ORG_ALIEN</manufacturer>
    <size>
      <x>1</x>
      <y>1</y>
      <z>1</z>
    </size>
    <image_offset>
      <x>32</x>
      <y>32</y>
    </image_offset>
    <shadow_offset>
      <x>32</x>
      <y>0</y>
    </shadow_offset>
    <stratmap>
      <sprite direction="n">PCKSTRAT:xcom3/UFODATA/STRATMAP.PCK:xcom3/UFODATA/STRATMAP.TAB:572</sprite>
    </stratmap>
    <animation>
      <frame>PCK:xcom3/UFODATA/SAUCER.PCK:xcom3/UFODATA/SAUCER.TAB:14</frame>
      <frame>PCK:xcom3/UFODATA/SAUCER.PCK:xcom3/UFODATA/SAUCER.TAB:15</frame>
      <frame>PCK:xcom3/UFODATA/SAUCER.PCK:xcom3/UFODATA/SAUCER.TAB:16</frame>
      <frame>PCK:xcom3/UFODATA/SAUCER.PCK:xcom3/UFODATA/SAUCER.TAB:17</frame>
      <frame>PCK:xcom3/UFODATA/SAUCER.PCK:xcom3/UFODATA/SAUCER.TAB:18</frame>
      <frame>PCK:xcom3/UFODATA/SAUCER.PCK:xcom3/UFODATA/SAUCER.TAB:19</frame>
      <frame>PCK:xcom3/UFODATA/SAUCER.PCK:xcom3/UFODATA/SAUCER.TAB:20</frame>
      <frame>PCK:xcom3/UFODATA/SAUCER.PCK:xcom3/UFODATA/SAUCER.TAB:21</frame>
      <frame>PCK:xcom3/UFODATA/SAUCER.PCK:xcom3/UFODATA/SAUCER.TAB:22</frame>
      <frame>PCK:xcom3/UFODATA/SAUCER.PCK:xcom3/UFODATA/SAUCER.TAB:23</frame>
      <frame>PCK:xcom3/UFODATA/SAUCER.PCK:xcom3/UFODATA/SAUCER.TAB:24</frame>
      <frame>PCK:xcom3/UFODATA/SAUCER.PCK:xcom3/UFODATA/SAUCER.TAB:25</frame>
    </animation>
    <crashed>PCK:xcom3/UFODATA/SAUCER.PCK:xcom3/UFODATA/SAUCER.TAB:26</crashed>
    <shadows>
      <sprite direction="n">PCKSHADOW:xcom3/UFODATA/SHADOW.PCK:xcom3/UFODATA/SHADOW.TAB:90</sprite>
    </shadows>
    <acceleration>2</acceleration>
    <top_speed>8</top_speed>
    <health>400</health>
    <crash_health>150</crash_health>
    <weight>5000</weight>
    <armour direction="rear">6</armour>
    <armour direction="top">6</armour>
    <armour direction="left">6</armour>
    <armour direction="right">6</armour>
    <armour direction="bottom">8</armour>
    <armour direction="front">4</armour>
    <passengers>3072</passengers>
    <aggressiveness>600</aggressiveness>
    <score>150</score>
    <icon>PCK:xcom3/ufodata/vs_icon.pck:xcom3/ufodata/vs_icon.tab:6:xcom3/ufodata/pal_01.dat</icon>
    <equipment_layout>
      <slot type="general" align_x="left" align_y="top">
        <p0>
          <x>4</x>
          <y>9</y>
        </p0>
        <p1>
          <x>12</x>
          <y>12</y>
        </p1>
      </slot>
      <slot type="weapon" align_x="centre" align_y="centre">
        <p0>
          <x>3</x>
          <y>4</y>
        </p0>
        <p1>
          <x>5</x>
          <y>8</y>
        </p1>
      </slot>
      <slot type="weapon" align_x="centre" align_y="centre">
        <p0>
          <x>11</x>
          <y>4</y>
        </p0>
        <p1>
          <x>13</x>
          <y>8</y>
        </p1>
      </slot>
      <slot type="weapon" align_x="centre" align_y="centre">
        <p0>
          <x>6</x>
          <y>4</y>
        </p0>
        <p1>
          <x>10</x>
          <y>8</y>
        </p1>
      </slot>
    </equipment_layout>
    <initial_equipment>
      <equipment>
        <type>VEQUIP_LIGHT_DISRUPTOR_BEAM</type>
        <position>
          <x>6</x>
          <y>4</y>
        </position>
      </equipment>
      <equipment>
        <type>VEQUIP_SMALL_DISRUPTION_SHIELD</type>
        <position>
          <x>4</x>
          <y>9</y>
        </position>
      </equipment>
    </initial_equipment>
  </vehicle>
</openapoc_rules>
